{
    "minecraft:netherite_sword": {
      "max_enchanting_slots": 10,
      "repair_scaling": 1.0
    },
    "minecraft:netherite_pickaxe": {
      "max_enchanting_slots": 10,
      "repair_scaling": 1.0
    },
    "minecraft:netherite_axe": {
      "max_enchanting_slots": 10,
      "repair_scaling": 1.0
    },
    "minecraft:netherite_hoe": {
      "max_enchanting_slots": 10,
      "repair_scaling": 1.0
    },
    "minecraft:netherite_shovel": {
      "max_enchanting_slots": 10,
      "repair_scaling": 1.0
    },
    "minecraft:netherite_helmet": {
      "max_enchanting_slots": 10,
      "repair_scaling": 1.0
    },
    "minecraft:netherite_chestplate": {
      "max_enchanting_slots": 10,
      "repair_scaling": 1.0
    },
    "minecraft:netherite_leggings": {
      "max_enchanting_slots": 10,
      "repair_scaling": 1.0
    },
    "minecraft:netherite_boots": {
      "max_enchanting_slots": 10,
      "repair_scaling": 1.0
    },
    "minecraft:diamond_sword": {
      "max_enchanting_slots": 10,
      "repair_scaling": 0.5
    },
    "minecraft:diamond_pickaxe": {
      "max_enchanting_slots": 10,
      "repair_scaling": 0.5
    },
    "minecraft:diamond_axe": {
      "max_enchanting_slots": 10,
      "repair_scaling": 0.5
    },
    "minecraft:diamond_hoe": {
      "max_enchanting_slots": 10,
      "repair_scaling": 0.5
    },
    "minecraft:diamond_shovel": {
      "max_enchanting_slots": 10,
      "repair_scaling": 0.5
    },
    "minecraft:diamond_helmet": {
      "max_enchanting_slots": 10,
      "repair_scaling": 0.5
    },
    "minecraft:diamond_chestplate": {
      "max_enchanting_slots": 10,
      "repair_scaling": 0.5
    },
    "minecraft:diamond_leggings": {
      "max_enchanting_slots": 10,
      "repair_scaling": 0.5
    },
    "minecraft:diamond_boots": {
      "max_enchanting_slots": 10,
      "repair_scaling": 0.5
    },
    "minecraft:golden_sword": {
      "max_enchanting_slots": 18,
      "repair_scaling": 1.0
    },
    "minecraft:golden_pickaxe": {
      "max_enchanting_slots": 18,
      "repair_scaling": 1.0
    },
    "minecraft:golden_axe": {
      "max_enchanting_slots": 18,
      "repair_scaling": 1.0
    },
    "minecraft:golden_hoe": {
      "max_enchanting_slots": 18,
      "repair_scaling": 1.0
    },
    "minecraft:golden_shovel": {
      "max_enchanting_slots": 18,
      "repair_scaling": 1.0
    },
    "minecraft:golden_helmet": {
      "max_enchanting_slots": 18,
      "repair_scaling": 1.0
    },
    "minecraft:golden_chestplate": {
      "max_enchanting_slots": 18,
      "repair_scaling": 1.0
    },
    "minecraft:golden_leggings": {
      "max_enchanting_slots": 18,
      "repair_scaling": 1.0
    },
    "minecraft:golden_boots": {
      "max_enchanting_slots": 18,
      "repair_scaling": 1.0
    },
    "minecraft:iron_sword": {
      "max_enchanting_slots": 12,
      "repair_scaling": 2.0
    },
    "minecraft:iron_pickaxe": {
      "max_enchanting_slots": 12,
      "repair_scaling": 2.0
    },
    "minecraft:iron_axe": {
      "max_enchanting_slots": 12,
      "repair_scaling": 2.0
    },
    "minecraft:iron_hoe": {
      "max_enchanting_slots": 12,
      "repair_scaling": 2.0
    },
    "minecraft:iron_shovel": {
      "max_enchanting_slots": 12,
      "repair_scaling": 2.0
    },
    "minecraft:iron_helmet": {
      "max_enchanting_slots": 12,
      "repair_scaling": 2.0
    },
    "minecraft:iron_chestplate": {
      "max_enchanting_slots": 12,
      "repair_scaling": 2.0
    },
    "minecraft:iron_leggings": {
      "max_enchanting_slots": 12,
      "repair_scaling": 2.0
    },
    "minecraft:iron_boots": {
      "max_enchanting_slots": 12,
      "repair_scaling": 2.0
    },
    "minecraft:stone_sword": {
      "max_enchanting_slots": 14,
      "repair_scaling": 2.0
    },
    "minecraft:stone_pickaxe": {
      "max_enchanting_slots": 14,
      "repair_scaling": 2.0
    },
    "minecraft:stone_axe": {
      "max_enchanting_slots": 14,
      "repair_scaling": 2.0
    },
    "minecraft:stone_hoe": {
      "max_enchanting_slots": 14,
      "repair_scaling": 2.0
    },
    "minecraft:stone_shovel": {
      "max_enchanting_slots": 14,
      "repair_scaling": 2.0
    },
    "minecraft:wooden_sword": {
      "max_enchanting_slots": 16,
      "repair_scaling": 2.0
    },
    "minecraft:wooden_pickaxe": {
      "max_enchanting_slots": 16,
      "repair_scaling": 2.0
    },
    "minecraft:wooden_axe": {
      "max_enchanting_slots": 16,
      "repair_scaling": 2.0
    },
    "minecraft:wooden_hoe": {
      "max_enchanting_slots": 16,
      "repair_scaling": 2.0
    },
    "minecraft:wooden_shovel": {
      "max_enchanting_slots": 16,
      "repair_scaling": 2.0
    },
    "minecraft:chainmail_helmet": {
      "max_enchanting_slots": 14,
      "repair_scaling": 1.0
    },
    "minecraft:chainmail_chestplate": {
      "max_enchanting_slots": 14,
      "repair_scaling": 1.0
    },
    "minecraft:chainmail_leggings": {
      "max_enchanting_slots": 14,
      "repair_scaling": 1.0
    },
    "minecraft:chainmail_boots": {
      "max_enchanting_slots": 14,
      "repair_scaling": 1.0
    },
    "minecraft:leather_helmet": {
      "max_enchanting_slots": 16,
      "repair_scaling": 1.0
    },
    "minecraft:leather_chestplate": {
      "max_enchanting_slots": 16,
      "repair_scaling": 1.0
    },
    "minecraft:leather_leggings": {
      "max_enchanting_slots": 16,
      "repair_scaling": 1.0
    },
    "minecraft:leather_boots": {
      "max_enchanting_slots": 16,
      "repair_scaling": 1.0
    },
    "minecraft:fishing_rod": {
      "max_enchanting_slots": 8,
      "repair_scaling": 4.0
    },
    "minecraft:crossbow": {
      "max_enchanting_slots": 7,
      "repair_scaling": 4.0
    },
    "minecraft:bow": {
      "max_enchanting_slots": 8,
      "repair_scaling": 4.0
    },
    "minecraft:trident": {
      "max_enchanting_slots": 8,
      "repair_scaling": 0.5
    },
    "minecraft:turtle_helmet": {
      "max_enchanting_slots": 15,
      "repair_scaling": 0.5
    },
    "minecraft:elytra": {
      "max_enchanting_slots": 6,
      "repair_scaling": 1.0
    },
    "minecraft:shears": {
      "max_enchanting_slots": 5,
      "repair_scaling": 1.0
    },
    "minecraft:flint_and_steel": {
      "max_enchanting_slots": 5,
      "repair_scaling": 1.0
    },
    "minecraft:shield": {
      "max_enchanting_slots": 5,
      "repair_scaling": 1.0
    },
    "minecraft:carrot_on_a_stick": {
      "max_enchanting_slots": 5,
      "repair_scaling": 1.0
    },
    "minecraft:warped_fungus_on_a_stick": {
      "max_enchanting_slots": 5,
      "repair_scaling": 1.0
    },
    "unitool:mattock": {
      "max_enchanting_slots": 5,
      "repair_scaling": 2.0
    },
    "carvepump:wooden_carver": {
      "max_enchanting_slots": 16,
      "repair_scaling": 2.0
    },
    "carvepump:stone_carver": {
      "max_enchanting_slots": 14,
      "repair_scaling": 2.0
    },
    "carvepump:iron_carver": {
      "max_enchanting_slots": 12,
      "repair_scaling": 2.0
    },
    "carvepump:gold_carver": {
      "max_enchanting_slots": 18,
      "repair_scaling": 1.0
    },
    "carvepump:diamond_carver": {
      "max_enchanting_slots": 10,
      "repair_scaling": 0.5
    },
    "carvepump:netherite_carver": {
      "max_enchanting_slots": 10,
      "repair_scaling": 1.0
    },
    "outvoted:wildfire_shield": {
      "max_enchanting_slots": 5,
      "repair_scaling": 1.0
    },
    "betterend:elytra_crystalite": {
      "max_enchanting_slots": 5,
      "repair_scaling": 1.0
    },
    "betterend:elytra_armored": {
      "max_enchanting_slots": 5,
      "repair_scaling": 1.0
    },
    "betterend:iron_hammer": {
      "max_enchanting_slots": 12,
      "repair_scaling": 2.0
    },
    "betterend:golden_hammer": {
      "max_enchanting_slots": 18,
      "repair_scaling": 1.0
    },
    "betterend:diamond_hammer": {
      "max_enchanting_slots": 10,
      "repair_scaling": 0.5
    },
    "betterend:netherite_hammer": {
      "max_enchanting_slots": 10,
      "repair_scaling": 1.0
    },
    "betterend:aeternium_sword": {
      "max_enchanting_slots": 8,
      "repair_scaling": 1.0
    },
    "betterend:aeternium_pickaxe": {
      "max_enchanting_slots": 8,
      "repair_scaling": 1.0
    },
    "betterend:aeternium_axe": {
      "max_enchanting_slots": 8,
      "repair_scaling": 1.0
    },
    "betterend:aeternium_hoe": {
      "max_enchanting_slots": 8,
      "repair_scaling": 1.0
    },
    "betterend:aeternium_hammer": {
      "max_enchanting_slots": 8,
      "repair_scaling": 1.0
    },
    "betterend:aeternium_shovel": {
      "max_enchanting_slots": 8,
      "repair_scaling": 1.0
    },
    "betterend:aeternium_helmet": {
      "max_enchanting_slots": 8,
      "repair_scaling": 1.0
    },
    "betterend:aeternium_chestplate": {
      "max_enchanting_slots": 8,
      "repair_scaling": 1.0
    },
    "betterend:aeternium_leggings": {
      "max_enchanting_slots": 8,
      "repair_scaling": 1.0
    },
    "betterend:aeternium_boots": {
      "max_enchanting_slots": 8,
      "repair_scaling": 1.0
    },
    "betterend:terminite_sword": {
      "max_enchanting_slots": 12,
      "repair_scaling": 0.5
    },
    "betterend:terminite_pickaxe": {
      "max_enchanting_slots": 12,
      "repair_scaling": 0.5
    },
    "betterend:terminite_axe": {
      "max_enchanting_slots": 12,
      "repair_scaling": 0.5
    },
    "betterend:terminite_hoe": {
      "max_enchanting_slots": 12,
      "repair_scaling": 0.5
    },
    "betterend:terminite_hammer": {
      "max_enchanting_slots": 12,
      "repair_scaling": 0.5
    },
    "betterend:terminite_shovel": {
      "max_enchanting_slots": 12,
      "repair_scaling": 0.5
    },
    "betterend:terminite_helmet": {
      "max_enchanting_slots": 12,
      "repair_scaling": 0.5
    },
    "betterend:terminite_chestplate": {
      "max_enchanting_slots": 12,
      "repair_scaling": 0.5
    },
    "betterend:terminite_leggings": {
      "max_enchanting_slots": 12,
      "repair_scaling": 0.5
    },
    "betterend:terminite_boots": {
      "max_enchanting_slots": 12,
      "repair_scaling": 0.5
    },
    "betterend:thallasium_sword": {
      "max_enchanting_slots": 12,
      "repair_scaling": 1.0
    },
    "betterend:thallasium_pickaxe": {
      "max_enchanting_slots": 12,
      "repair_scaling": 1.0
    },
    "betterend:thallasium_axe": {
      "max_enchanting_slots": 12,
      "repair_scaling": 1.0
    },
    "betterend:thallasium_hoe": {
      "max_enchanting_slots": 12,
      "repair_scaling": 1.0
    },
    "betterend:thallasium_hammer": {
      "max_enchanting_slots": 12,
      "repair_scaling": 1.0
    },
    "betterend:thallasium_shovel": {
      "max_enchanting_slots": 12,
      "repair_scaling": 1.0
    },
    "betterend:crystalite_helmet": {
      "max_enchanting_slots": 6,
      "repair_scaling": 1.0
    },
    "betterend:crystalite_chestplate": {
      "max_enchanting_slots": 6,
      "repair_scaling": 1.0
    },
    "betterend:crystalite_leggings": {
      "max_enchanting_slots": 6,
      "repair_scaling": 1.0
    },
    "betterend:crystalite_boots": {
      "max_enchanting_slots": 6,
      "repair_scaling": 1.0
    },
    "betternether:cincinnasite_shears": {
      "max_enchanting_slots": 5,
      "repair_scaling": 1.0
    },
    "betternether:cincinnasite_sword": {
      "max_enchanting_slots": 8,
      "repair_scaling": 1.0
    },
    "betternether:cincinnasite_axe": {
      "max_enchanting_slots": 8,
      "repair_scaling": 1.0
    },
    "betternether:cincinnasite_shovel": {
      "max_enchanting_slots": 8,
      "repair_scaling": 1.0
    },
    "betternether:cincinnasite_hoe": {
      "max_enchanting_slots": 8,
      "repair_scaling": 1.0
    },
    "betternether:cincinnasite_pickaxe": {
      "max_enchanting_slots": 8,
      "repair_scaling": 1.0
    },
    "betternether:cincinnasite_helmet": {
      "max_enchanting_slots": 8,
      "repair_scaling": 1.0
    },
    "betternether:cincinnasite_chestplate": {
      "max_enchanting_slots": 8,
      "repair_scaling": 1.0
    },
    "betternether:cincinnasite_leggings": {
      "max_enchanting_slots": 8,
      "repair_scaling": 1.0
    },
    "betternether:cincinnasite_boots": {
      "max_enchanting_slots": 8,
      "repair_scaling": 1.0
    },
    "betternether:cincinnasite_sword_diamond": {
      "max_enchanting_slots": 8,
      "repair_scaling": 2.0
    },
    "betternether:cincinnasite_axe_diamond": {
      "max_enchanting_slots": 8,
      "repair_scaling": 2.0
    },
    "betternether:cincinnasite_shovel_diamond": {
      "max_enchanting_slots": 8,
      "repair_scaling": 2.0
    },
    "betternether:cincinnasite_hoe_diamond": {
      "max_enchanting_slots": 8,
      "repair_scaling": 2.0
    },
    "betternether:cincinnasite_pickaxe_diamond": {
      "max_enchanting_slots": 8,
      "repair_scaling": 2.0
    },
    "betternether:nether_ruby_sword": {
      "max_enchanting_slots": 11,
      "repair_scaling": 1.0
    },
    "betternether:nether_ruby_axe": {
      "max_enchanting_slots": 11,
      "repair_scaling": 1.0
    },
    "betternether:nether_ruby_shovel": {
      "max_enchanting_slots": 11,
      "repair_scaling": 1.0
    },
    "betternether:nether_ruby_hoe": {
      "max_enchanting_slots": 11,
      "repair_scaling": 1.0
    },
    "betternether:nether_ruby_pickaxe": {
      "max_enchanting_slots": 11,
      "repair_scaling": 1.0
    },
    "betternether:nether_ruby_helmet": {
      "max_enchanting_slots": 11,
      "repair_scaling": 1.0
    },
    "betternether:nether_ruby_chestplate": {
      "max_enchanting_slots": 11,
      "repair_scaling": 1.0
    },
    "betternether:nether_ruby_leggings": {
      "max_enchanting_slots": 11,
      "repair_scaling": 1.0
    },
    "betternether:nether_ruby_boots": {
      "max_enchanting_slots": 11,
      "repair_scaling": 1.0
    },
    "adventurez:stone_golem_helmet": {
      "max_enchanting_slots": 12,
      "repair_scaling": 0.3
    },
    "adventurez:stone_golem_chestplate": {
      "max_enchanting_slots": 12,
      "repair_scaling": 0.3
    },
    "adventurez:stone_golem_leggings": {
      "max_enchanting_slots": 12,
      "repair_scaling": 0.3
    },
    "adventurez:stone_golem_boots": {
      "max_enchanting_slots": 12,
      "repair_scaling": 0.3
    },
    "adventurez:ender_flute": {
      "max_enchanting_slots": 5,
      "repair_scaling": 1.0
    },
    "adventurez:chorus_fruit_on_a_stick": {
      "max_enchanting_slots": 5,
      "repair_scaling": 1.0
    },
    "wolveswitharmor:leather_wolf_armor": {
      "max_enchanting_slots": 16,
      "repair_scaling": 1.0
    },
    "wolveswitharmor:iron_wolf_armor": {
      "max_enchanting_slots": 12,
      "repair_scaling": 2.0
    },
    "wolveswitharmor:golden_wolf_armor": {
      "max_enchanting_slots": 18,
      "repair_scaling": 1.0
    },
    "wolveswitharmor:diamond_wolf_armor": {
      "max_enchanting_slots": 10,
      "repair_scaling": 0.5
    },
    "wolveswitharmor:netherite_wolf_armor": {
      "max_enchanting_slots": 10,
      "repair_scaling": 1.0
    },
    "gateofbabylon:netherite_dagger": {
      "max_enchanting_slots": 10,
      "repair_scaling": 1.0
    },
    "gateofbabylon:netherite_spear": {
      "max_enchanting_slots": 10,
      "repair_scaling": 1.0
    },
    "gateofbabylon:netherite_broadsword": {
      "max_enchanting_slots": 10,
      "repair_scaling": 1.0
    },
    "gateofbabylon:netherite_rapier": {
      "max_enchanting_slots": 10,
      "repair_scaling": 1.0
    },
    "gateofbabylon:netherite_haladie": {
      "max_enchanting_slots": 10,
      "repair_scaling": 1.0
    },
    "gateofbabylon:netherite_waraxe": {
      "max_enchanting_slots": 10,
      "repair_scaling": 1.0
    },
    "gateofbabylon:netherite_katana": {
      "max_enchanting_slots": 10,
      "repair_scaling": 1.0
    },
    "gateofbabylon:netherite_bow": {
      "max_enchanting_slots": 10,
      "repair_scaling": 1.0
    },
    "gateofbabylon:netherite_shield": {
      "max_enchanting_slots": 10,
      "repair_scaling": 1.0
    },
    "gateofbabylon:netherite_yoyo": {
      "max_enchanting_slots": 10,
      "repair_scaling": 1.0
    },
    "gateofbabylon:netherite_boomerang": {
      "max_enchanting_slots": 10,
      "repair_scaling": 1.0
    },
    "gateofbabylon:diamond_dagger": {
      "max_enchanting_slots": 10,
      "repair_scaling": 0.5
    },
    "gateofbabylon:diamond_spear": {
      "max_enchanting_slots": 10,
      "repair_scaling": 0.5
    },
    "gateofbabylon:diamond_broadsword": {
      "max_enchanting_slots": 10,
      "repair_scaling": 0.5
    },
    "gateofbabylon:diamond_rapier": {
      "max_enchanting_slots": 10,
      "repair_scaling": 0.5
    },
    "gateofbabylon:diamond_haladie": {
      "max_enchanting_slots": 10,
      "repair_scaling": 0.5
    },
    "gateofbabylon:diamond_waraxe": {
      "max_enchanting_slots": 10,
      "repair_scaling": 0.5
    },
    "gateofbabylon:diamond_katana": {
      "max_enchanting_slots": 10,
      "repair_scaling": 0.5
    },
    "gateofbabylon:diamond_bow": {
      "max_enchanting_slots": 10,
      "repair_scaling": 0.5
    },
    "gateofbabylon:diamond_shield": {
      "max_enchanting_slots": 10,
      "repair_scaling": 0.5
    },
    "gateofbabylon:diamond_yoyo": {
      "max_enchanting_slots": 10,
      "repair_scaling": 0.5
    },
    "gateofbabylon:diamond_boomerang": {
      "max_enchanting_slots": 10,
      "repair_scaling": 0.5
    },
    "gateofbabylon:golden_dagger": {
      "max_enchanting_slots": 18,
      "repair_scaling": 1.0
    },
    "gateofbabylon:golden_spear": {
      "max_enchanting_slots": 18,
      "repair_scaling": 1.0
    },
    "gateofbabylon:golden_broadsword": {
      "max_enchanting_slots": 18,
      "repair_scaling": 1.0
    },
    "gateofbabylon:golden_rapier": {
      "max_enchanting_slots": 18,
      "repair_scaling": 1.0
    },
    "gateofbabylon:golden_haladie": {
      "max_enchanting_slots": 18,
      "repair_scaling": 1.0
    },
    "gateofbabylon:golden_waraxe": {
      "max_enchanting_slots": 18,
      "repair_scaling": 1.0
    },
    "gateofbabylon:golden_katana": {
      "max_enchanting_slots": 18,
      "repair_scaling": 1.0
    },
    "gateofbabylon:golden_bow": {
      "max_enchanting_slots": 18,
      "repair_scaling": 1.0
    },
    "gateofbabylon:golden_shield": {
      "max_enchanting_slots": 18,
      "repair_scaling": 1.0
    },
    "gateofbabylon:golden_yoyo": {
      "max_enchanting_slots": 18,
      "repair_scaling": 1.0
    },
    "gateofbabylon:golden_boomerang": {
      "max_enchanting_slots": 18,
      "repair_scaling": 1.0
    },
    "gateofbabylon:iron_dagger": {
      "max_enchanting_slots": 12,
      "repair_scaling": 2.0
    },
    "gateofbabylon:iron_spear": {
      "max_enchanting_slots": 12,
      "repair_scaling": 2.0
    },
    "gateofbabylon:iron_broadsword": {
      "max_enchanting_slots": 12,
      "repair_scaling": 2.0
    },
    "gateofbabylon:iron_rapier": {
      "max_enchanting_slots": 12,
      "repair_scaling": 2.0
    },
    "gateofbabylon:iron_haladie": {
      "max_enchanting_slots": 12,
      "repair_scaling": 2.0
    },
    "gateofbabylon:iron_waraxe": {
      "max_enchanting_slots": 12,
      "repair_scaling": 2.0
    },
    "gateofbabylon:iron_katana": {
      "max_enchanting_slots": 12,
      "repair_scaling": 2.0
    },
    "gateofbabylon:iron_bow": {
      "max_enchanting_slots": 12,
      "repair_scaling": 2.0
    },
    "gateofbabylon:iron_shield": {
      "max_enchanting_slots": 12,
      "repair_scaling": 2.0
    },
    "gateofbabylon:iron_yoyo": {
      "max_enchanting_slots": 12,
      "repair_scaling": 2.0
    },
    "gateofbabylon:iron_boomerang": {
      "max_enchanting_slots": 12,
      "repair_scaling": 2.0
    },
    "gateofbabylon:stone_dagger": {
      "max_enchanting_slots": 14,
      "repair_scaling": 2.0
    },
    "gateofbabylon:stone_spear": {
      "max_enchanting_slots": 14,
      "repair_scaling": 2.0
    },
    "gateofbabylon:stone_broadsword": {
      "max_enchanting_slots": 14,
      "repair_scaling": 2.0
    },
    "gateofbabylon:stone_rapier": {
      "max_enchanting_slots": 14,
      "repair_scaling": 2.0
    },
    "gateofbabylon:stone_haladie": {
      "max_enchanting_slots": 14,
      "repair_scaling": 2.0
    },
    "gateofbabylon:stone_waraxe": {
      "max_enchanting_slots": 14,
      "repair_scaling": 2.0
    },
    "gateofbabylon:stone_katana": {
      "max_enchanting_slots": 14,
      "repair_scaling": 2.0
    },
    "gateofbabylon:stone_bow": {
      "max_enchanting_slots": 14,
      "repair_scaling": 2.0
    },
    "gateofbabylon:stone_shield": {
      "max_enchanting_slots": 14,
      "repair_scaling": 2.0
    },
    "gateofbabylon:stone_yoyo": {
      "max_enchanting_slots": 14,
      "repair_scaling": 2.0
    },
    "gateofbabylon:stone_boomerang": {
      "max_enchanting_slots": 14,
      "repair_scaling": 2.0
    },
    "gateofbabylon:wooden_dagger": {
      "max_enchanting_slots": 16,
      "repair_scaling": 2.0
    },
    "gateofbabylon:wooden_spear": {
      "max_enchanting_slots": 16,
      "repair_scaling": 2.0
    },
    "gateofbabylon:wooden_broadsword": {
      "max_enchanting_slots": 16,
      "repair_scaling": 2.0
    },
    "gateofbabylon:wooden_rapier": {
      "max_enchanting_slots": 16,
      "repair_scaling": 2.0
    },
    "gateofbabylon:wooden_haladie": {
      "max_enchanting_slots": 16,
      "repair_scaling": 2.0
    },
    "gateofbabylon:wooden_waraxe": {
      "max_enchanting_slots": 16,
      "repair_scaling": 2.0
    },
    "gateofbabylon:wooden_katana": {
      "max_enchanting_slots": 16,
      "repair_scaling": 2.0
    },
    "gateofbabylon:wooden_bow": {
      "max_enchanting_slots": 16,
      "repair_scaling": 2.0
    },
    "gateofbabylon:wooden_shield": {
      "max_enchanting_slots": 16,
      "repair_scaling": 2.0
    },
    "gateofbabylon:wooden_yoyo": {
      "max_enchanting_slots": 16,
      "repair_scaling": 2.0
    },
    "gateofbabylon:wooden_boomerang": {
      "max_enchanting_slots": 16,
      "repair_scaling": 2.0
    },
    "dragonloot:dragon_helmet": {
      "max_enchanting_slots": 8,
      "repair_scaling": 1.0
    },
    "dragonloot:dragon_chestplate": {
      "max_enchanting_slots": 8,
      "repair_scaling": 1.0
    },
    "dragonloot:dragon_leggings": {
      "max_enchanting_slots": 8,
      "repair_scaling": 1.0
    },
    "dragonloot:dragon_boots": {
      "max_enchanting_slots": 8,
      "repair_scaling": 1.0
    },
    "dragonloot:dragon_pickaxe": {
      "max_enchanting_slots": 8,
      "repair_scaling": 1.0
    },
    "dragonloot:dragon_shovel": {
      "max_enchanting_slots": 8,
      "repair_scaling": 1.0
    },
    "dragonloot:dragon_axe": {
      "max_enchanting_slots": 8,
      "repair_scaling": 1.0
    },
    "dragonloot:dragon_hoe": {
      "max_enchanting_slots": 8,
      "repair_scaling": 1.0
    },
    "dragonloot:dragon_sword": {
      "max_enchanting_slots": 8,
      "repair_scaling": 1.0
    },
    "dragonloot:dragon_crossbow": {
      "max_enchanting_slots": 6,
      "repair_scaling": 1.0
    },
    "dragonloot:dragon_bow": {
      "max_enchanting_slots": 6,
      "repair_scaling": 1.0
    },
    "dragonloot:dragon_trident": {
      "max_enchanting_slots": 6,
      "repair_scaling": 1.0
    },
    "ratsmischief:rat_mask": {
      "max_enchanting_slots": 18,
      "repair_scaling": 1.0
    },
    "farmersdelight:flint_knife": {
      "max_enchanting_slots": 14,
      "repair_scaling": 2.0
    },
    "farmersdelight:iron_knife": {
      "max_enchanting_slots": 12,
      "repair_scaling": 2.0
    },
    "farmersdelight:golden_knife": {
      "max_enchanting_slots": 18,
      "repair_scaling": 1.0
    },
    "farmersdelight:diamond_knife": {
      "max_enchanting_slots": 10,
      "repair_scaling": 0.5
    },
    "farmersdelight:netherite_knife": {
      "max_enchanting_slots": 10,
      "repair_scaling": 1.0
    },
    "nethersdelight:iron_machete": {
      "max_enchanting_slots": 12,
      "repair_scaling": 2.0
    },
    "nethersdelight:golden_machete": {
      "max_enchanting_slots": 18,
      "repair_scaling": 1.0
    },
    "nethersdelight:diamond_machete": {
      "max_enchanting_slots": 10,
      "repair_scaling": 0.5
    },
    "nethersdelight:netherite_machete": {
      "max_enchanting_slots": 10,
      "repair_scaling": 1.0
    },
    "consistency_plus:turtle_chestplate": {
      "max_enchanting_slots": 15,
      "repair_scaling": 0.5
    },
    "consistency_plus:turtle_leggings": {
      "max_enchanting_slots": 15,
      "repair_scaling": 0.5
    },
    "consistency_plus:turtle_boots": {
      "max_enchanting_slots": 15,
      "repair_scaling": 0.5
    },
    "valley:rg_helmet": {
      "max_enchanting_slots": 18,
      "repair_scaling": 0.5
    },
    "valley:rg_chestplate": {
      "max_enchanting_slots": 18,
      "repair_scaling": 0.5
    },
    "valley:rg_leggings": {
      "max_enchanting_slots": 18,
      "repair_scaling": 0.5
    },
    "valley:rg_boots": {
      "max_enchanting_slots": 18,
      "repair_scaling": 0.5
    },
    "valley:rg_sword": {
      "max_enchanting_slots": 18,
      "repair_scaling": 0.5
    },
    "valley:rg_axe": {
      "max_enchanting_slots": 18,
      "repair_scaling": 0.5
    },
    "valley:rg_shovel": {
      "max_enchanting_slots": 18,
      "repair_scaling": 0.5
    },
    "valley:rg_hoe": {
      "max_enchanting_slots": 18,
      "repair_scaling": 0.5
    },
    "valley:rg_pickaxe": {
      "max_enchanting_slots": 18,
      "repair_scaling": 0.5
    },
    "valley:wood_knife": {
      "max_enchanting_slots": 16,
      "repair_scaling": 2.0
    },
    "valley:stone_knife": {
      "max_enchanting_slots": 14,
      "repair_scaling": 2.0
    },
    "valley:iron_knife": {
      "max_enchanting_slots": 12,
      "repair_scaling": 2.0
    },
    "valley:golden_knife": {
      "max_enchanting_slots": 18,
      "repair_scaling": 1.0
    },
    "valley:diamond_knife": {
      "max_enchanting_slots": 10,
      "repair_scaling": 0.5
    },
    "valley:netherite_knife": {
      "max_enchanting_slots": 10,
      "repair_scaling": 1.0
    },
    "valley:rg_knife": {
      "max_enchanting_slots": 18,
      "repair_scaling": 0.5
    },
    "valley:bone_knife": {
      "max_enchanting_slots": 5,
      "repair_scaling": 1.0
    },
    "valley:wood_sickle": {
      "max_enchanting_slots": 16,
      "repair_scaling": 2.0
    },
    "valley:stone_sickle": {
      "max_enchanting_slots": 14,
      "repair_scaling": 2.0
    },
    "valley:iron_sickle": {
      "max_enchanting_slots": 12,
      "repair_scaling": 2.0
    },
    "valley:golden_sickle": {
      "max_enchanting_slots": 18,
      "repair_scaling": 1.0
    },
    "valley:diamond_sickle": {
      "max_enchanting_slots": 10,
      "repair_scaling": 0.5
    },
    "valley:netherite_sickle": {
      "max_enchanting_slots": 10,
      "repair_scaling": 1.0
    },
    "valley:rg_sickle": {
      "max_enchanting_slots": 18,
      "repair_scaling": 0.5
    },
    "valley:wood_hatchet": {
      "max_enchanting_slots": 16,
      "repair_scaling": 2.0
    },
    "valley:stone_hatchet": {
      "max_enchanting_slots": 14,
      "repair_scaling": 2.0
    },
    "valley:iron_hatchet": {
      "max_enchanting_slots": 12,
      "repair_scaling": 2.0
    },
    "valley:golden_hatchet": {
      "max_enchanting_slots": 18,
      "repair_scaling": 1.0
    },
    "valley:diamond_hatchet": {
      "max_enchanting_slots": 10,
      "repair_scaling": 0.5
    },
    "valley:netherite_hatchet": {
      "max_enchanting_slots": 10,
      "repair_scaling": 1.0
    },
    "valley:rg_hatchet": {
      "max_enchanting_slots": 18,
      "repair_scaling": 0.5
    },
    "valley:turtle_chestplate": {
      "max_enchanting_slots": 15,
      "repair_scaling": 0.5
    },
    "valley:turtle_leggings": {
      "max_enchanting_slots": 15,
      "repair_scaling": 0.5
    },
    "valley:turtle_boots": {
      "max_enchanting_slots": 15,
      "repair_scaling": 0.5
    },
    "valley:tongs": {
      "max_enchanting_slots": 5,
      "repair_scaling": 1.0
    },
    "valley:lumber_axe": {
      "max_enchanting_slots": 12,
      "repair_scaling": 2.0
    },
    "valley:fur_chestplate": {
      "max_enchanting_slots": 16,
      "repair_scaling": 1.0
    },
    "impaled:pitchfork": {
      "max_enchanting_slots": 12,
      "repair_scaling": 2.0
    },
    "impaled:atlan": {
      "max_enchanting_slots": 18,
      "repair_scaling": 1.0
    },
    "impaled:elder_trident": {
      "max_enchanting_slots": 10,
      "repair_scaling": 0.5
    },
    "impaled:hellfork": {
      "max_enchanting_slots": 10,
      "repair_scaling": 1.0
    },
    "harvest_scythes:wooden_scythe": {
      "max_enchanting_slots": 16,
      "repair_scaling": 2.0
    },
    "harvest_scythes:stone_scythe": {
      "max_enchanting_slots": 14,
      "repair_scaling": 2.0
    },
    "harvest_scythes:iron_scythe": {
      "max_enchanting_slots": 12,
      "repair_scaling": 2.0
    },
    "harvest_scythes:golden_scythe": {
      "max_enchanting_slots": 18,
      "repair_scaling": 1.0
    },
    "harvest_scythes:diamond_scythe": {
      "max_enchanting_slots": 10,
      "repair_scaling": 0.5
    },
    "harvest_scythes:netherite_scythe": {
      "max_enchanting_slots": 10,
      "repair_scaling": 1.0
    },
    "harvest_scythes:wooden_machete": {
      "max_enchanting_slots": 16,
      "repair_scaling": 2.0
    },
    "harvest_scythes:stone_machete": {
      "max_enchanting_slots": 14,
      "repair_scaling": 2.0
    },
    "harvest_scythes:iron_machete": {
      "max_enchanting_slots": 12,
      "repair_scaling": 2.0
    },
    "harvest_scythes:golden_machete": {
      "max_enchanting_slots": 18,
      "repair_scaling": 1.0
    },
    "harvest_scythes:diamond_machete": {
      "max_enchanting_slots": 10,
      "repair_scaling": 0.5
    },
    "harvest_scythes:netherite_machete": {
      "max_enchanting_slots": 10,
      "repair_scaling": 1.0
    },
    "gofish:skeletal_rod": {
      "max_enchanting_slots": 5,
      "repair_scaling": 1.0
    },
    "gofish:blaze_rod": {
      "max_enchanting_slots": 10,
      "repair_scaling": 0.5
    },
    "gofish:soul_rod": {
      "max_enchanting_slots": 10,
      "repair_scaling": 1.0
    },
    "gofish:diamond_reinforced_rod": {
      "max_enchanting_slots": 10,
      "repair_scaling": 0.5
    },
    "gofish:ender_rod": {
      "max_enchanting_slots": 10,
      "repair_scaling": 0.5
    },
    "gofish:matrix_rod": {
      "max_enchanting_slots": 10,
      "repair_scaling": 0.5
    },
    "gofish:frosted_rod": {
      "max_enchanting_slots": 12,
      "repair_scaling": 2.0
    },
    "gofish:slime_rod": {
      "max_enchanting_slots": 12,
      "repair_scaling": 2.0
    },
    "gofish:celestial_rod": {
      "max_enchanting_slots": 18,
      "repair_scaling": 1.0
    },
    "additionaladditions:rose_gold_helmet": {
      "max_enchanting_slots": 18,
      "repair_scaling": 0.5
    },
    "additionaladditions:rose_gold_chestplate": {
      "max_enchanting_slots": 18,
      "repair_scaling": 0.5
    },
    "additionaladditions:rose_gold_leggings": {
      "max_enchanting_slots": 18,
      "repair_scaling": 0.5
    },
    "additionaladditions:rose_gold_boots": {
      "max_enchanting_slots": 18,
      "repair_scaling": 0.5
    },
    "additionaladditions:rose_gold_sword": {
      "max_enchanting_slots": 18,
      "repair_scaling": 0.5
    },
    "additionaladditions:rose_gold_axe": {
      "max_enchanting_slots": 18,
      "repair_scaling": 0.5
    },
    "additionaladditions:rose_gold_shovel": {
      "max_enchanting_slots": 18,
      "repair_scaling": 0.5
    },
    "additionaladditions:rose_gold_hoe": {
      "max_enchanting_slots": 18,
      "repair_scaling": 0.5
    },
    "additionaladditions:rose_gold_pickaxe": {
      "max_enchanting_slots": 18,
      "repair_scaling": 0.5
    },
    "additionaladditions:gilded_netherite_helmet": {
      "max_enchanting_slots": 12,
      "repair_scaling": 0.3
    },
    "additionaladditions:gilded_netherite_chestplate": {
      "max_enchanting_slots": 12,
      "repair_scaling": 0.3
    },
    "additionaladditions:gilded_netherite_leggings": {
      "max_enchanting_slots": 12,
      "repair_scaling": 0.3
    },
    "additionaladditions:gilded_netherite_boots": {
      "max_enchanting_slots": 12,
      "repair_scaling": 0.3
    },
    "additionaladditions:gilded_netherite_sword": {
      "max_enchanting_slots": 12,
      "repair_scaling": 0.3
    },
    "additionaladditions:gilded_netherite_axe": {
      "max_enchanting_slots": 12,
      "repair_scaling": 0.3
    },
    "additionaladditions:gilded_netherite_shovel": {
      "max_enchanting_slots": 12,
      "repair_scaling": 0.3
    },
    "additionaladditions:gilded_netherite_hoe": {
      "max_enchanting_slots": 12,
      "repair_scaling": 0.3
    },
    "additionaladditions:gilded_netherite_pickaxe": {
      "max_enchanting_slots": 12,
      "repair_scaling": 0.3
    },
    "additionaladditions:crossbow_with_spyglass": {
      "max_enchanting_slots": 7,
      "repair_scaling": 4.0
    },
    "oxidized:rose_gold_sword": {
      "max_enchanting_slots": 18,
      "repair_scaling": 0.5
    },
    "oxidized:rose_gold_axe": {
      "max_enchanting_slots": 18,
      "repair_scaling": 0.5
    },
    "oxidized:rose_gold_shovel": {
      "max_enchanting_slots": 18,
      "repair_scaling": 0.5
    },
    "oxidized:rose_gold_hoe": {
      "max_enchanting_slots": 18,
      "repair_scaling": 0.5
    },
    "oxidized:rose_gold_pickaxe": {
      "max_enchanting_slots": 18,
      "repair_scaling": 0.5
    },
    "conjuring:soul_alloy_sword": {
      "max_enchanting_slots": 15,
      "repair_scaling": 1.0
    },
    "conjuring:soul_alloy_shovel": {
      "max_enchanting_slots": 15,
      "repair_scaling": 1.0
    },
    "conjuring:soul_alloy_hatchet": {
      "max_enchanting_slots": 15,
      "repair_scaling": 1.0
    },
    "conjuring:soul_alloy_pickaxe": {
      "max_enchanting_slots": 15,
      "repair_scaling": 1.0
    },
    "mythicmetals:adamantite_sword": {
      "max_enchanting_slots": 10,
      "repair_scaling": 1.0
    },
    "mythicmetals:adamantite_axe": {
      "max_enchanting_slots": 10,
      "repair_scaling": 1.0
    },
    "mythicmetals:adamantite_shovel": {
      "max_enchanting_slots": 10,
      "repair_scaling": 1.0
    },
    "mythicmetals:adamantite_hoe": {
      "max_enchanting_slots": 10,
      "repair_scaling": 1.0
    },
    "mythicmetals:adamantite_pickaxe": {
      "max_enchanting_slots": 10,
      "repair_scaling": 1.0
    },
    "mythicmetals:adamantite_helmet": {
      "max_enchanting_slots": 10,
      "repair_scaling": 1.0
    },
    "mythicmetals:adamantite_chestplate": {
      "max_enchanting_slots": 10,
      "repair_scaling": 1.0
    },
    "mythicmetals:adamantite_leggings": {
      "max_enchanting_slots": 10,
      "repair_scaling": 1.0
    },
    "mythicmetals:adamantite_boots": {
      "max_enchanting_slots": 10,
      "repair_scaling": 1.0
    },
    "mythicmetals:aquarium_sword": {
      "max_enchanting_slots": 15,
      "repair_scaling": 2.0
    },
    "mythicmetals:aquarium_axe": {
      "max_enchanting_slots": 15,
      "repair_scaling": 2.0
    },
    "mythicmetals:aquarium_shovel": {
      "max_enchanting_slots": 15,
      "repair_scaling": 2.0
    },
    "mythicmetals:aquarium_hoe": {
      "max_enchanting_slots": 15,
      "repair_scaling": 2.0
    },
    "mythicmetals:aquarium_pickaxe": {
      "max_enchanting_slots": 15,
      "repair_scaling": 2.0
    },
    "mythicmetals:aquarium_helmet": {
      "max_enchanting_slots": 15,
      "repair_scaling": 2.0
    },
    "mythicmetals:aquarium_chestplate": {
      "max_enchanting_slots": 15,
      "repair_scaling": 2.0
    },
    "mythicmetals:aquarium_leggings": {
      "max_enchanting_slots": 15,
      "repair_scaling": 2.0
    },
    "mythicmetals:aquarium_boots": {
      "max_enchanting_slots": 15,
      "repair_scaling": 2.0
    },
    "mythicmetals:tidesinger_sword": {
      "max_enchanting_slots": 17,
      "repair_scaling": 3.0
    },
    "mythicmetals:tidesinger_axe": {
      "max_enchanting_slots": 17,
      "repair_scaling": 3.0
    },
    "mythicmetals:tidesinger_shovel": {
      "max_enchanting_slots": 17,
      "repair_scaling": 3.0
    },
    "mythicmetals:tidesinger_hoe": {
      "max_enchanting_slots": 17,
      "repair_scaling": 3.0
    },
    "mythicmetals:tidesinger_pickaxe": {
      "max_enchanting_slots": 17,
      "repair_scaling": 3.0
    },
    "mythicmetals:tidesinger_helmet": {
      "max_enchanting_slots": 17,
      "repair_scaling": 3.0
    },
    "mythicmetals:tidesinger_chestplate": {
      "max_enchanting_slots": 17,
      "repair_scaling": 3.0
    },
    "mythicmetals:tidesinger_leggings": {
      "max_enchanting_slots": 17,
      "repair_scaling": 3.0
    },
    "mythicmetals:tidesinger_boots": {
      "max_enchanting_slots": 17,
      "repair_scaling": 3.0
    },
    "mythicmetals:banglum_sword": {
      "max_enchanting_slots": 5,
      "repair_scaling": 4.0
    },
    "mythicmetals:banglum_axe": {
      "max_enchanting_slots": 5,
      "repair_scaling": 4.0
    },
    "mythicmetals:banglum_shovel": {
      "max_enchanting_slots": 5,
      "repair_scaling": 4.0
    },
    "mythicmetals:banglum_hoe": {
      "max_enchanting_slots": 5,
      "repair_scaling": 4.0
    },
    "mythicmetals:banglum_pickaxe": {
      "max_enchanting_slots": 5,
      "repair_scaling": 4.0
    },
    "mythicmetals:banglum_helmet": {
      "max_enchanting_slots": 5,
      "repair_scaling": 4.0
    },
    "mythicmetals:banglum_chestplate": {
      "max_enchanting_slots": 5,
      "repair_scaling": 4.0
    },
    "mythicmetals:banglum_leggings": {
      "max_enchanting_slots": 5,
      "repair_scaling": 4.0
    },
    "mythicmetals:banglum_boots": {
      "max_enchanting_slots": 5,
      "repair_scaling": 4.0
    },
    "mythicmetals:bronze_sword": {
      "max_enchanting_slots": 8,
      "repair_scaling": 1.0
    },
    "mythicmetals:bronze_axe": {
      "max_enchanting_slots": 8,
      "repair_scaling": 1.0
    },
    "mythicmetals:bronze_shovel": {
      "max_enchanting_slots": 8,
      "repair_scaling": 1.0
    },
    "mythicmetals:bronze_hoe": {
      "max_enchanting_slots": 8,
      "repair_scaling": 1.0
    },
    "mythicmetals:bronze_pickaxe": {
      "max_enchanting_slots": 8,
      "repair_scaling": 1.0
    },
    "mythicmetals:bronze_helmet": {
      "max_enchanting_slots": 8,
      "repair_scaling": 1.0
    },
    "mythicmetals:bronze_chestplate": {
      "max_enchanting_slots": 8,
      "repair_scaling": 1.0
    },
    "mythicmetals:bronze_leggings": {
      "max_enchanting_slots": 8,
      "repair_scaling": 1.0
    },
    "mythicmetals:bronze_boots": {
      "max_enchanting_slots": 8,
      "repair_scaling": 1.0
    },
    "mythicmetals:carmot_sword": {
      "max_enchanting_slots": 16,
      "repair_scaling": 1.5
    },
    "mythicmetals:carmot_axe": {
      "max_enchanting_slots": 16,
      "repair_scaling": 1.5
    },
    "mythicmetals:carmot_shovel": {
      "max_enchanting_slots": 16,
      "repair_scaling": 1.5
    },
    "mythicmetals:carmot_hoe": {
      "max_enchanting_slots": 16,
      "repair_scaling": 1.5
    },
    "mythicmetals:carmot_pickaxe": {
      "max_enchanting_slots": 16,
      "repair_scaling": 1.5
    },
    "mythicmetals:carmot_helmet": {
      "max_enchanting_slots": 16,
      "repair_scaling": 1.5
    },
    "mythicmetals:carmot_chestplate": {
      "max_enchanting_slots": 16,
      "repair_scaling": 1.5
    },
    "mythicmetals:carmot_leggings": {
      "max_enchanting_slots": 16,
      "repair_scaling": 1.5
    },
    "mythicmetals:carmot_boots": {
      "max_enchanting_slots": 16,
      "repair_scaling": 1.5
    },
    "mythicmetals:celestium_sword": {
      "max_enchanting_slots": 18,
      "repair_scaling": 0.5
    },
    "mythicmetals:celestium_axe": {
      "max_enchanting_slots": 18,
      "repair_scaling": 0.5
    },
    "mythicmetals:celestium_shovel": {
      "max_enchanting_slots": 18,
      "repair_scaling": 0.5
    },
    "mythicmetals:celestium_hoe": {
      "max_enchanting_slots": 18,
      "repair_scaling": 0.5
    },
    "mythicmetals:celestium_pickaxe": {
      "max_enchanting_slots": 18,
      "repair_scaling": 0.5
    },
    "mythicmetals:celestium_helmet": {
      "max_enchanting_slots": 18,
      "repair_scaling": 0.5
    },
    "mythicmetals:celestium_chestplate": {
      "max_enchanting_slots": 18,
      "repair_scaling": 0.5
    },
    "mythicmetals:celestium_leggings": {
      "max_enchanting_slots": 18,
      "repair_scaling": 0.5
    },
    "mythicmetals:celestium_boots": {
      "max_enchanting_slots": 18,
      "repair_scaling": 0.5
    },
    "mythicmetals:celestium_elytra": {
      "max_enchanting_slots": 5,
      "repair_scaling": 1.0
    },
    "mythicmetals:copper_sword": {
      "max_enchanting_slots": 12,
      "repair_scaling": 1.0
    },
    "mythicmetals:copper_axe": {
      "max_enchanting_slots": 12,
      "repair_scaling": 1.0
    },
    "mythicmetals:copper_shovel": {
      "max_enchanting_slots": 12,
      "repair_scaling": 1.0
    },
    "mythicmetals:copper_hoe": {
      "max_enchanting_slots": 12,
      "repair_scaling": 1.0
    },
    "mythicmetals:copper_pickaxe": {
      "max_enchanting_slots": 12,
      "repair_scaling": 1.0
    },
    "mythicmetals:copper_helmet": {
      "max_enchanting_slots": 12,
      "repair_scaling": 1.0
    },
    "mythicmetals:copper_chestplate": {
      "max_enchanting_slots": 12,
      "repair_scaling": 1.0
    },
    "mythicmetals:copper_leggings": {
      "max_enchanting_slots": 12,
      "repair_scaling": 1.0
    },
    "mythicmetals:copper_boots": {
      "max_enchanting_slots": 12,
      "repair_scaling": 1.0
    },
    "mythicmetals:durasteel_sword": {
      "max_enchanting_slots": 8,
      "repair_scaling": 1.0
    },
    "mythicmetals:durasteel_axe": {
      "max_enchanting_slots": 8,
      "repair_scaling": 1.0
    },
    "mythicmetals:durasteel_shovel": {
      "max_enchanting_slots": 8,
      "repair_scaling": 1.0
    },
    "mythicmetals:durasteel_hoe": {
      "max_enchanting_slots": 8,
      "repair_scaling": 1.0
    },
    "mythicmetals:durasteel_pickaxe": {
      "max_enchanting_slots": 8,
      "repair_scaling": 1.0
    },
    "mythicmetals:durasteel_helmet": {
      "max_enchanting_slots": 8,
      "repair_scaling": 1.0
    },
    "mythicmetals:durasteel_chestplate": {
      "max_enchanting_slots": 8,
      "repair_scaling": 1.0
    },
    "mythicmetals:durasteel_leggings": {
      "max_enchanting_slots": 8,
      "repair_scaling": 1.0
    },
    "mythicmetals:durasteel_boots": {
      "max_enchanting_slots": 8,
      "repair_scaling": 1.0
    },
    "mythicmetals:hallowed_sword": {
      "max_enchanting_slots": 15,
      "repair_scaling": 2.0
    },
    "mythicmetals:hallowed_axe": {
      "max_enchanting_slots": 15,
      "repair_scaling": 2.0
    },
    "mythicmetals:hallowed_shovel": {
      "max_enchanting_slots": 15,
      "repair_scaling": 2.0
    },
    "mythicmetals:hallowed_hoe": {
      "max_enchanting_slots": 15,
      "repair_scaling": 2.0
    },
    "mythicmetals:hallowed_pickaxe": {
      "max_enchanting_slots": 15,
      "repair_scaling": 2.0
    },
    "mythicmetals:hallowed_helmet": {
      "max_enchanting_slots": 15,
      "repair_scaling": 2.0
    },
    "mythicmetals:hallowed_chestplate": {
      "max_enchanting_slots": 15,
      "repair_scaling": 2.0
    },
    "mythicmetals:hallowed_leggings": {
      "max_enchanting_slots": 15,
      "repair_scaling": 2.0
    },
    "mythicmetals:hallowed_boots": {
      "max_enchanting_slots": 15,
      "repair_scaling": 2.0
    },
    "mythicmetals:kyber_sword": {
      "max_enchanting_slots": 16,
      "repair_scaling": 1.0
    },
    "mythicmetals:kyber_axe": {
      "max_enchanting_slots": 16,
      "repair_scaling": 1.0
    },
    "mythicmetals:kyber_shovel": {
      "max_enchanting_slots": 16,
      "repair_scaling": 1.0
    },
    "mythicmetals:kyber_hoe": {
      "max_enchanting_slots": 16,
      "repair_scaling": 1.0
    },
    "mythicmetals:kyber_pickaxe": {
      "max_enchanting_slots": 16,
      "repair_scaling": 1.0
    },
    "mythicmetals:kyber_helmet": {
      "max_enchanting_slots": 16,
      "repair_scaling": 1.0
    },
    "mythicmetals:kyber_chestplate": {
      "max_enchanting_slots": 16,
      "repair_scaling": 1.0
    },
    "mythicmetals:kyber_leggings": {
      "max_enchanting_slots": 16,
      "repair_scaling": 1.0
    },
    "mythicmetals:kyber_boots": {
      "max_enchanting_slots": 16,
      "repair_scaling": 1.0
    },
    "mythicmetals:legendary_banglum_sword": {
      "max_enchanting_slots": 10,
      "repair_scaling": 4.0
    },
    "mythicmetals:legendary_banglum_axe": {
      "max_enchanting_slots": 10,
      "repair_scaling": 4.0
    },
    "mythicmetals:legendary_banglum_shovel": {
      "max_enchanting_slots": 10,
      "repair_scaling": 4.0
    },
    "mythicmetals:legendary_banglum_hoe": {
      "max_enchanting_slots": 10,
      "repair_scaling": 4.0
    },
    "mythicmetals:legendary_banglum_pickaxe": {
      "max_enchanting_slots": 10,
      "repair_scaling": 4.0
    },
    "mythicmetals:legendary_banglum_helmet": {
      "max_enchanting_slots": 10,
      "repair_scaling": 4.0
    },
    "mythicmetals:legendary_banglum_chestplate": {
      "max_enchanting_slots": 10,
      "repair_scaling": 4.0
    },
    "mythicmetals:legendary_banglum_leggings": {
      "max_enchanting_slots": 10,
      "repair_scaling": 4.0
    },
    "mythicmetals:legendary_banglum_boots": {
      "max_enchanting_slots": 10,
      "repair_scaling": 4.0
    },
    "mythicmetals:metallurgium_sword": {
      "max_enchanting_slots": 16,
      "repair_scaling": 2.0
    },
    "mythicmetals:metallurgium_axe": {
      "max_enchanting_slots": 16,
      "repair_scaling": 2.0
    },
    "mythicmetals:metallurgium_shovel": {
      "max_enchanting_slots": 16,
      "repair_scaling": 2.0
    },
    "mythicmetals:metallurgium_hoe": {
      "max_enchanting_slots": 16,
      "repair_scaling": 2.0
    },
    "mythicmetals:metallurgium_pickaxe": {
      "max_enchanting_slots": 16,
      "repair_scaling": 2.0
    },
    "mythicmetals:metallurgium_helmet": {
      "max_enchanting_slots": 16,
      "repair_scaling": 2.0
    },
    "mythicmetals:metallurgium_chestplate": {
      "max_enchanting_slots": 16,
      "repair_scaling": 2.0
    },
    "mythicmetals:metallurgium_leggings": {
      "max_enchanting_slots": 16,
      "repair_scaling": 2.0
    },
    "mythicmetals:metallurgium_boots": {
      "max_enchanting_slots": 16,
      "repair_scaling": 2.0
    },
    "mythicmetals:midas_gold_sword": {
      "max_enchanting_slots": 24,
      "repair_scaling": 3.0
    },
    "mythicmetals:midas_gold_axe": {
      "max_enchanting_slots": 24,
      "repair_scaling": 3.0
    },
    "mythicmetals:midas_gold_shovel": {
      "max_enchanting_slots": 24,
      "repair_scaling": 3.0
    },
    "mythicmetals:midas_gold_hoe": {
      "max_enchanting_slots": 24,
      "repair_scaling": 3.0
    },
    "mythicmetals:midas_gold_pickaxe": {
      "max_enchanting_slots": 24,
      "repair_scaling": 3.0
    },
    "mythicmetals:midas_gold_helmet": {
      "max_enchanting_slots": 24,
      "repair_scaling": 3.0
    },
    "mythicmetals:midas_gold_chestplate": {
      "max_enchanting_slots": 24,
      "repair_scaling": 3.0
    },
    "mythicmetals:midas_gold_leggings": {
      "max_enchanting_slots": 24,
      "repair_scaling": 3.0
    },
    "mythicmetals:midas_gold_boots": {
      "max_enchanting_slots": 24,
      "repair_scaling": 3.0
    },
    "mythicmetals:gilded_midas_gold_sword": {
      "max_enchanting_slots": 26,
      "repair_scaling": 3.0
    },
    "mythicmetals:royal_midas_gold_sword": {
      "max_enchanting_slots": 28,
      "repair_scaling": 3.0
    },
    "mythicmetals:mythril_sword": {
      "max_enchanting_slots": 10,
      "repair_scaling": 1.0
    },
    "mythicmetals:mythril_axe": {
      "max_enchanting_slots": 10,
      "repair_scaling": 1.0
    },
    "mythicmetals:mythril_shovel": {
      "max_enchanting_slots": 10,
      "repair_scaling": 1.0
    },
    "mythicmetals:mythril_hoe": {
      "max_enchanting_slots": 10,
      "repair_scaling": 1.0
    },
    "mythicmetals:mythril_pickaxe": {
      "max_enchanting_slots": 10,
      "repair_scaling": 1.0
    },
    "mythicmetals:mythril_helmet": {
      "max_enchanting_slots": 10,
      "repair_scaling": 1.0
    },
    "mythicmetals:mythril_chestplate": {
      "max_enchanting_slots": 10,
      "repair_scaling": 1.0
    },
    "mythicmetals:mythril_leggings": {
      "max_enchanting_slots": 10,
      "repair_scaling": 1.0
    },
    "mythicmetals:mythril_boots": {
      "max_enchanting_slots": 10,
      "repair_scaling": 1.0
    },
    "mythicmetals:mythril_drill": {
      "max_enchanting_slots": 15,
      "repair_scaling": 0.5
    },
    "mythicmetals:orichalcum_sword": {
      "max_enchanting_slots": 10,
      "repair_scaling": 1.0
    },
    "mythicmetals:orichalcum_axe": {
      "max_enchanting_slots": 10,
      "repair_scaling": 1.0
    },
    "mythicmetals:orichalcum_shovel": {
      "max_enchanting_slots": 10,
      "repair_scaling": 1.0
    },
    "mythicmetals:orichalcum_hoe": {
      "max_enchanting_slots": 10,
      "repair_scaling": 1.0
    },
    "mythicmetals:orichalcum_pickaxe": {
      "max_enchanting_slots": 10,
      "repair_scaling": 1.0
    },
    "mythicmetals:orichalcum_helmet": {
      "max_enchanting_slots": 10,
      "repair_scaling": 1.0
    },
    "mythicmetals:orichalcum_chestplate": {
      "max_enchanting_slots": 10,
      "repair_scaling": 1.0
    },
    "mythicmetals:orichalcum_leggings": {
      "max_enchanting_slots": 10,
      "repair_scaling": 1.0
    },
    "mythicmetals:orichalcum_boots": {
      "max_enchanting_slots": 10,
      "repair_scaling": 1.0
    },
    "mythicmetals:orichalcum_hammer": {
      "max_enchanting_slots": 12,
      "repair_scaling": 0.5
    },
    "mythicmetals:osmium_sword": {
      "max_enchanting_slots": 12,
      "repair_scaling": 1.0
    },
    "mythicmetals:osmium_axe": {
      "max_enchanting_slots": 12,
      "repair_scaling": 1.0
    },
    "mythicmetals:osmium_shovel": {
      "max_enchanting_slots": 12,
      "repair_scaling": 1.0
    },
    "mythicmetals:osmium_hoe": {
      "max_enchanting_slots": 12,
      "repair_scaling": 1.0
    },
    "mythicmetals:osmium_pickaxe": {
      "max_enchanting_slots": 12,
      "repair_scaling": 1.0
    },
    "mythicmetals:osmium_helmet": {
      "max_enchanting_slots": 12,
      "repair_scaling": 1.0
    },
    "mythicmetals:osmium_chestplate": {
      "max_enchanting_slots": 12,
      "repair_scaling": 1.0
    },
    "mythicmetals:osmium_leggings": {
      "max_enchanting_slots": 12,
      "repair_scaling": 1.0
    },
    "mythicmetals:osmium_boots": {
      "max_enchanting_slots": 12,
      "repair_scaling": 1.0
    },
    "mythicmetals:osmium_chainmail_helmet": {
      "max_enchanting_slots": 15,
      "repair_scaling": 1.0
    },
    "mythicmetals:osmium_chainmail_chestplate": {
      "max_enchanting_slots": 15,
      "repair_scaling": 1.0
    },
    "mythicmetals:osmium_chainmail_leggings": {
      "max_enchanting_slots": 15,
      "repair_scaling": 1.0
    },
    "mythicmetals:osmium_chainmail_boots": {
      "max_enchanting_slots": 15,
      "repair_scaling": 1.0
    },
    "mythicmetals:palladium_sword": {
      "max_enchanting_slots": 20,
      "repair_scaling": 2.0
    },
    "mythicmetals:palladium_axe": {
      "max_enchanting_slots": 20,
      "repair_scaling": 2.0
    },
    "mythicmetals:palladium_shovel": {
      "max_enchanting_slots": 20,
      "repair_scaling": 2.0
    },
    "mythicmetals:palladium_hoe": {
      "max_enchanting_slots": 20,
      "repair_scaling": 2.0
    },
    "mythicmetals:palladium_pickaxe": {
      "max_enchanting_slots": 20,
      "repair_scaling": 2.0
    },
    "mythicmetals:palladium_helmet": {
      "max_enchanting_slots": 20,
      "repair_scaling": 2.0
    },
    "mythicmetals:palladium_chestplate": {
      "max_enchanting_slots": 20,
      "repair_scaling": 2.0
    },
    "mythicmetals:palladium_leggings": {
      "max_enchanting_slots": 20,
      "repair_scaling": 2.0
    },
    "mythicmetals:palladium_boots": {
      "max_enchanting_slots": 20,
      "repair_scaling": 2.0
    },
    "mythicmetals:prometheum_sword": {
      "max_enchanting_slots": 16,
      "repair_scaling": 5.0
    },
    "mythicmetals:prometheum_axe": {
      "max_enchanting_slots": 16,
      "repair_scaling": 5.0
    },
    "mythicmetals:prometheum_shovel": {
      "max_enchanting_slots": 16,
      "repair_scaling": 5.0
    },
    "mythicmetals:prometheum_hoe": {
      "max_enchanting_slots": 16,
      "repair_scaling": 5.0
    },
    "mythicmetals:prometheum_pickaxe": {
      "max_enchanting_slots": 16,
      "repair_scaling": 5.0
    },
    "mythicmetals:prometheum_helmet": {
      "max_enchanting_slots": 16,
      "repair_scaling": 5.0
    },
    "mythicmetals:prometheum_chestplate": {
      "max_enchanting_slots": 16,
      "repair_scaling": 5.0
    },
    "mythicmetals:prometheum_leggings": {
      "max_enchanting_slots": 16,
      "repair_scaling": 5.0
    },
    "mythicmetals:prometheum_boots": {
      "max_enchanting_slots": 16,
      "repair_scaling": 5.0
    },
    "mythicmetals:quadrillum_sword": {
      "max_enchanting_slots": 5,
      "repair_scaling": 2.0
    },
    "mythicmetals:quadrillum_axe": {
      "max_enchanting_slots": 5,
      "repair_scaling": 2.0
    },
    "mythicmetals:quadrillum_shovel": {
      "max_enchanting_slots": 5,
      "repair_scaling": 2.0
    },
    "mythicmetals:quadrillum_hoe": {
      "max_enchanting_slots": 5,
      "repair_scaling": 2.0
    },
    "mythicmetals:quadrillum_pickaxe": {
      "max_enchanting_slots": 5,
      "repair_scaling": 2.0
    },
    "mythicmetals:runite_sword": {
      "max_enchanting_slots": 15,
      "repair_scaling": 1.0
    },
    "mythicmetals:runite_axe": {
      "max_enchanting_slots": 15,
      "repair_scaling": 1.0
    },
    "mythicmetals:runite_shovel": {
      "max_enchanting_slots": 15,
      "repair_scaling": 1.0
    },
    "mythicmetals:runite_hoe": {
      "max_enchanting_slots": 15,
      "repair_scaling": 1.0
    },
    "mythicmetals:runite_pickaxe": {
      "max_enchanting_slots": 15,
      "repair_scaling": 1.0
    },
    "mythicmetals:runite_helmet": {
      "max_enchanting_slots": 15,
      "repair_scaling": 1.0
    },
    "mythicmetals:runite_chestplate": {
      "max_enchanting_slots": 15,
      "repair_scaling": 1.0
    },
    "mythicmetals:runite_leggings": {
      "max_enchanting_slots": 15,
      "repair_scaling": 1.0
    },
    "mythicmetals:runite_boots": {
      "max_enchanting_slots": 15,
      "repair_scaling": 1.0
    },
    "mythicmetals:silver_helmet": {
      "max_enchanting_slots": 9,
      "repair_scaling": 1.0
    },
    "mythicmetals:silver_chestplate": {
      "max_enchanting_slots": 9,
      "repair_scaling": 1.0
    },
    "mythicmetals:silver_leggings": {
      "max_enchanting_slots": 9,
      "repair_scaling": 1.0
    },
    "mythicmetals:silver_boots": {
      "max_enchanting_slots": 9,
      "repair_scaling": 1.0
    },
    "mythicmetals:star_platinum_sword": {
      "max_enchanting_slots": 22,
      "repair_scaling": 3.0
    },
    "mythicmetals:star_platinum_axe": {
      "max_enchanting_slots": 22,
      "repair_scaling": 3.0
    },
    "mythicmetals:star_platinum_shovel": {
      "max_enchanting_slots": 22,
      "repair_scaling": 3.0
    },
    "mythicmetals:star_platinum_hoe": {
      "max_enchanting_slots": 22,
      "repair_scaling": 3.0
    },
    "mythicmetals:star_platinum_pickaxe": {
      "max_enchanting_slots": 22,
      "repair_scaling": 3.0
    },
    "mythicmetals:star_platinum_helmet": {
      "max_enchanting_slots": 22,
      "repair_scaling": 3.0
    },
    "mythicmetals:star_platinum_chestplate": {
      "max_enchanting_slots": 22,
      "repair_scaling": 3.0
    },
    "mythicmetals:star_platinum_leggings": {
      "max_enchanting_slots": 22,
      "repair_scaling": 3.0
    },
    "mythicmetals:star_platinum_boots": {
      "max_enchanting_slots": 22,
      "repair_scaling": 3.0
    },
    "mythicmetals:steel_sword": {
      "max_enchanting_slots": 8,
      "repair_scaling": 1.5
    },
    "mythicmetals:steel_axe": {
      "max_enchanting_slots": 8,
      "repair_scaling": 1.5
    },
    "mythicmetals:steel_shovel": {
      "max_enchanting_slots": 8,
      "repair_scaling": 1.5
    },
    "mythicmetals:steel_hoe": {
      "max_enchanting_slots": 8,
      "repair_scaling": 1.5
    },
    "mythicmetals:steel_pickaxe": {
      "max_enchanting_slots": 8,
      "repair_scaling": 1.5
    },
    "mythicmetals:steel_helmet": {
      "max_enchanting_slots": 8,
      "repair_scaling": 1.5
    },
    "mythicmetals:steel_chestplate": {
      "max_enchanting_slots": 8,
      "repair_scaling": 1.5
    },
    "mythicmetals:steel_leggings": {
      "max_enchanting_slots": 8,
      "repair_scaling": 1.5
    },
    "mythicmetals:steel_boots": {
      "max_enchanting_slots": 8,
      "repair_scaling": 1.5
    },
    "mythicmetals:stormyx_sword": {
      "max_enchanting_slots": 24,
      "repair_scaling": 1.0
    },
    "mythicmetals:stormyx_axe": {
      "max_enchanting_slots": 24,
      "repair_scaling": 1.0
    },
    "mythicmetals:stormyx_shovel": {
      "max_enchanting_slots": 24,
      "repair_scaling": 1.0
    },
    "mythicmetals:stormyx_hoe": {
      "max_enchanting_slots": 24,
      "repair_scaling": 1.0
    },
    "mythicmetals:stormyx_pickaxe": {
      "max_enchanting_slots": 24,
      "repair_scaling": 1.0
    },
    "mythicmetals:stormyx_helmet": {
      "max_enchanting_slots": 24,
      "repair_scaling": 1.0
    },
    "mythicmetals:stormyx_chestplate": {
      "max_enchanting_slots": 24,
      "repair_scaling": 1.0
    },
    "mythicmetals:stormyx_leggings": {
      "max_enchanting_slots": 24,
      "repair_scaling": 1.0
    },
    "mythicmetals:stormyx_boots": {
      "max_enchanting_slots": 24,
      "repair_scaling": 1.0
    },
    "mythicmetals:stormyx_shield": {
      "max_enchanting_slots": 24,
      "repair_scaling": 1.0
    },
    "mythicmetals:red_aegis_sword": {
      "max_enchanting_slots": 20,
      "repair_scaling": 2.0
    },
    "mythicmetals:white_aegis_sword": {
      "max_enchanting_slots": 20,
      "repair_scaling": 2.0
    },
    "mythicupgrades:jade_sword": {
      "max_enchanting_slots": 20,
      "repair_scaling": 3.0
    },
    "mythicupgrades:jade_axe": {
      "max_enchanting_slots": 20,
      "repair_scaling": 3.0
    },
    "mythicupgrades:jade_helmet": {
      "max_enchanting_slots": 20,
      "repair_scaling": 3.0
    },
    "mythicupgrades:jade_chestplate": {
      "max_enchanting_slots": 20,
      "repair_scaling": 3.0
    },
    "mythicupgrades:jade_leggings": {
      "max_enchanting_slots": 20,
      "repair_scaling": 3.0
    },
    "mythicupgrades:jade_boots": {
      "max_enchanting_slots": 20,
      "repair_scaling": 3.0
    },
    "mythicupgrades:topaz_sword": {
      "max_enchanting_slots": 20,
      "repair_scaling": 3.0
    },
    "mythicupgrades:topaz_axe": {
      "max_enchanting_slots": 20,
      "repair_scaling": 3.0
    },
    "mythicupgrades:topaz_shovel": {
      "max_enchanting_slots": 20,
      "repair_scaling": 3.0
    },
    "mythicupgrades:topaz_hoe": {
      "max_enchanting_slots": 20,
      "repair_scaling": 3.0
    },
    "mythicupgrades:topaz_pickaxe": {
      "max_enchanting_slots": 20,
      "repair_scaling": 3.0
    },
    "mythicupgrades:topaz_helmet": {
      "max_enchanting_slots": 20,
      "repair_scaling": 3.0
    },
    "mythicupgrades:topaz_chestplate": {
      "max_enchanting_slots": 20,
      "repair_scaling": 3.0
    },
    "mythicupgrades:topaz_leggings": {
      "max_enchanting_slots": 20,
      "repair_scaling": 3.0
    },
    "mythicupgrades:topaz_boots": {
      "max_enchanting_slots": 20,
      "repair_scaling": 3.0
    },
    "mythicupgrades:aquamarine_sword": {
      "max_enchanting_slots": 20,
      "repair_scaling": 3.0
    },
    "mythicupgrades:aquamarine_axe": {
      "max_enchanting_slots": 20,
      "repair_scaling": 3.0
    },
    "mythicupgrades:sapphire_sword": {
      "max_enchanting_slots": 20,
      "repair_scaling": 3.0
    },
    "mythicupgrades:sapphire_axe": {
      "max_enchanting_slots": 20,
      "repair_scaling": 3.0
    },
    "mythicupgrades:sapphire_helmet": {
      "max_enchanting_slots": 20,
      "repair_scaling": 3.0
    },
    "mythicupgrades:sapphire_chestplate": {
      "max_enchanting_slots": 20,
      "repair_scaling": 3.0
    },
    "mythicupgrades:sapphire_leggings": {
      "max_enchanting_slots": 20,
      "repair_scaling": 3.0
    },
    "mythicupgrades:sapphire_boots": {
      "max_enchanting_slots": 20,
      "repair_scaling": 3.0
    },
    "mythicupgrades:ruby_sword": {
      "max_enchanting_slots": 20,
      "repair_scaling": 3.0
    },
    "mythicupgrades:ruby_axe": {
      "max_enchanting_slots": 20,
      "repair_scaling": 3.0
    },
    "mythicupgrades:ruby_shovel": {
      "max_enchanting_slots": 20,
      "repair_scaling": 3.0
    },
    "mythicupgrades:ruby_hoe": {
      "max_enchanting_slots": 20,
      "repair_scaling": 3.0
    },
    "mythicupgrades:ruby_pickaxe": {
      "max_enchanting_slots": 20,
      "repair_scaling": 3.0
    },
    "mythicupgrades:ametrine_sword": {
      "max_enchanting_slots": 20,
      "repair_scaling": 3.0
    },
    "mythicupgrades:ametrine_axe": {
      "max_enchanting_slots": 20,
      "repair_scaling": 3.0
    },
    "mythicupgrades:ametrine_helmet": {
      "max_enchanting_slots": 20,
      "repair_scaling": 3.0
    },
    "mythicupgrades:ametrine_chestplate": {
      "max_enchanting_slots": 20,
      "repair_scaling": 3.0
    },
    "mythicupgrades:ametrine_leggings": {
      "max_enchanting_slots": 20,
      "repair_scaling": 3.0
    },
    "mythicupgrades:ametrine_boots": {
      "max_enchanting_slots": 20,
      "repair_scaling": 3.0
    },
    "aquamirae:terrible_sword": {
      "max_enchanting_slots": 8,
      "repair_scaling": 1.0
    },
    "aquamirae:fin_cutter": {
      "max_enchanting_slots": 8,
      "repair_scaling": 1.0
    },
    "aquamirae:terrible_helmet": {
      "max_enchanting_slots": 8,
      "repair_scaling": 1.0
    },
    "aquamirae:terrible_chestplate": {
      "max_enchanting_slots": 8,
      "repair_scaling": 1.0
    },
    "aquamirae:terrible_leggings": {
      "max_enchanting_slots": 8,
      "repair_scaling": 1.0
    },
    "aquamirae:terrible_boots": {
      "max_enchanting_slots": 8,
      "repair_scaling": 1.0
    },
    "aquamirae:divider": {
      "max_enchanting_slots": 16,
      "repair_scaling": 1.0
    },
    "aquamirae:whisper_of_the_abyss": {
      "max_enchanting_slots": 16,
      "repair_scaling": 1.0
    },
    "aquamirae:abyssal_heaume": {
      "max_enchanting_slots": 16,
      "repair_scaling": 1.0
    },
    "aquamirae:abyssal_brigantine": {
      "max_enchanting_slots": 16,
      "repair_scaling": 1.0
    },
    "aquamirae:abyssal_leggings": {
      "max_enchanting_slots": 16,
      "repair_scaling": 1.0
    },
    "aquamirae:abyssal_boots": {
      "max_enchanting_slots": 16,
      "repair_scaling": 1.0
    },
    "aquamirae:abyssal_tiara": {
      "max_enchanting_slots": 16,
      "repair_scaling": 1.0
    },
    "aquamirae:remnants_saber": {
      "max_enchanting_slots": 10,
      "repair_scaling": 1.0
    },
    "aquamirae:poisoned_blade": {
      "max_enchanting_slots": 10,
      "repair_scaling": 1.0
    },
    "aquamirae:three_bolt_helmet": {
      "max_enchanting_slots": 10,
      "repair_scaling": 1.0
    },
    "aquamirae:three_bolt_suit": {
      "max_enchanting_slots": 10,
      "repair_scaling": 1.0
    },
    "aquamirae:three_bolt_leggings": {
      "max_enchanting_slots": 10,
      "repair_scaling": 1.0
    },
    "aquamirae:three_bolt_boots": {
      "max_enchanting_slots": 10,
      "repair_scaling": 1.0
    },
    "aquamirae:coral_lance": {
      "max_enchanting_slots": 20,
      "repair_scaling": 1.0
    },
    "aquamirae:sweet_lance": {
      "max_enchanting_slots": 22,
      "repair_scaling": 1.0
    },
    "aquamirae:poisoned_chakra": {
      "max_enchanting_slots": 10,
      "repair_scaling": 1.0
    },
    "aquamirae:maze_rose": {
      "max_enchanting_slots": 15,
      "repair_scaling": 1.0
    },
    "amarite:amarite_longsword": {
      "max_enchanting_slots": 20,
      "repair_scaling": 2.0
    },
    "winterly:cryomarble_sword": {
      "max_enchanting_slots": 14,
      "repair_scaling": 1.5
    },
    "winterly:cryomarble_axe": {
      "max_enchanting_slots": 14,
      "repair_scaling": 1.5
    },
    "winterly:cryomarble_shovel": {
      "max_enchanting_slots": 14,
      "repair_scaling": 1.5
    },
    "winterly:cryomarble_hoe": {
      "max_enchanting_slots": 14,
      "repair_scaling": 1.5
    },
    "winterly:cryomarble_pickaxe": {
      "max_enchanting_slots": 14,
      "repair_scaling": 1.5
    },
    "biomemakeover:cladded_helmet": {
      "max_enchanting_slots": 16,
      "repair_scaling": 1.0
    },
    "biomemakeover:cladded_chestplate": {
      "max_enchanting_slots": 16,
      "repair_scaling": 1.0
    },
    "biomemakeover:cladded_leggings": {
      "max_enchanting_slots": 16,
      "repair_scaling": 1.0
    },
    "biomemakeover:cladded_boots": {
      "max_enchanting_slots": 16,
      "repair_scaling": 1.0
    },
    "galosphere:sterling_helmet": {
      "max_enchanting_slots": 16,
      "repair_scaling": 1.0
    },
    "galosphere:sterling_chestplate": {
      "max_enchanting_slots": 16,
      "repair_scaling": 1.0
    },
    "galosphere:sterling_leggings": {
      "max_enchanting_slots": 16,
      "repair_scaling": 1.0
    },
    "galosphere:sterling_boots": {
      "max_enchanting_slots": 16,
      "repair_scaling": 1.0
    },
    "clutter:white_butterfly_elytra": {
      "max_enchanting_slots": 6,
      "repair_scaling": 1.0
    },
    "clutter:light_gray_butterfly_elytra": {
      "max_enchanting_slots": 6,
      "repair_scaling": 1.0
    },
    "clutter:gray_butterfly_elytra": {
      "max_enchanting_slots": 6,
      "repair_scaling": 1.0
    },
    "clutter:black_butterfly_elytra": {
      "max_enchanting_slots": 6,
      "repair_scaling": 1.0
    },
    "clutter:brown_butterfly_elytra": {
      "max_enchanting_slots": 6,
      "repair_scaling": 1.0
    },
    "clutter:red_butterfly_elytra": {
      "max_enchanting_slots": 6,
      "repair_scaling": 1.0
    },
    "clutter:orange_butterfly_elytra": {
      "max_enchanting_slots": 6,
      "repair_scaling": 1.0
    },
    "clutter:yellow_butterfly_elytra": {
      "max_enchanting_slots": 6,
      "repair_scaling": 1.0
    },
    "clutter:lime_butterfly_elytra": {
      "max_enchanting_slots": 6,
      "repair_scaling": 1.0
    },
    "clutter:green_butterfly_elytra": {
      "max_enchanting_slots": 6,
      "repair_scaling": 1.0
    },
    "clutter:cyan_butterfly_elytra": {
      "max_enchanting_slots": 6,
      "repair_scaling": 1.0
    },
    "clutter:light_blue_butterfly_elytra": {
      "max_enchanting_slots": 6,
      "repair_scaling": 1.0
    },
    "clutter:blue_butterfly_elytra": {
      "max_enchanting_slots": 6,
      "repair_scaling": 1.0
    },
    "clutter:purple_butterfly_elytra": {
      "max_enchanting_slots": 6,
      "repair_scaling": 1.0
    },
    "clutter:magenta_butterfly_elytra": {
      "max_enchanting_slots": 6,
      "repair_scaling": 1.0
    },
    "clutter:pink_butterfly_elytra": {
      "max_enchanting_slots": 6,
      "repair_scaling": 1.0
    },
    "clutter:crimson_butterfly_elytra": {
      "max_enchanting_slots": 6,
      "repair_scaling": 1.0
    },
    "clutter:warped_butterfly_elytra": {
      "max_enchanting_slots": 6,
      "repair_scaling": 1.0
    },
    "clutter:soul_butterfly_elytra": {
      "max_enchanting_slots": 6,
      "repair_scaling": 1.0
    },
    "clutter:silver_helmet": {
      "max_enchanting_slots": 14,
      "repair_scaling": 1.0
    },
    "clutter:silver_chestplate": {
      "max_enchanting_slots": 14,
      "repair_scaling": 1.0
    },
    "clutter:silver_leggings": {
      "max_enchanting_slots": 14,
      "repair_scaling": 1.0
    },
    "clutter:silver_boots": {
      "max_enchanting_slots": 14,
      "repair_scaling": 1.0
    },
    "frostiful:fur_helmet": {
      "max_enchanting_slots": 16,
      "repair_scaling": 1.0
    },
    "frostiful:fur_chestplate": {
      "max_enchanting_slots": 16,
      "repair_scaling": 1.0
    },
    "frostiful:fur_leggings": {
      "max_enchanting_slots": 16,
      "repair_scaling": 1.0
    },
    "frostiful:fur_boots": {
      "max_enchanting_slots": 16,
      "repair_scaling": 1.0
    },
    "frostiful:ice_skates": {
      "max_enchanting_slots": 16,
      "repair_scaling": 1.0
    },
    "frostiful:fur_padded_chainmail_helmet": {
      "max_enchanting_slots": 14,
      "repair_scaling": 1.0
    },
    "frostiful:fur_padded_chainmail_chestplate": {
      "max_enchanting_slots": 14,
      "repair_scaling": 1.0
    },
    "frostiful:fur_padded_chainmail_leggings": {
      "max_enchanting_slots": 14,
      "repair_scaling": 1.0
    },
    "frostiful:fur_padded_chainmail_boots": {
      "max_enchanting_slots": 14,
      "repair_scaling": 1.0
    },
    "frostiful:armored_ice_skates": {
      "max_enchanting_slots": 14,
      "repair_scaling": 1.0
    },
    "create:netherite_diving_helmet": {
      "max_enchanting_slots": 10,
      "repair_scaling": 1.0
    },
    "create:netherite_diving_boots": {
      "max_enchanting_slots": 10,
      "repair_scaling": 1.0
    },
    "create:copper_diving_helmet": {
      "max_enchanting_slots": 12,
      "repair_scaling": 1.0
    },
    "create:copper_diving_boots": {
      "max_enchanting_slots": 12,
      "repair_scaling": 1.0
    },
    "garnished:wooden_hatchet": {
      "max_enchanting_slots": 16,
      "repair_scaling": 2.0
    },
    "garnished:stone_hatchet": {
      "max_enchanting_slots": 14,
      "repair_scaling": 2.0
    },
    "garnished:iron_hatchet": {
      "max_enchanting_slots": 12,
      "repair_scaling": 2.0
    },
    "garnished:golden_hatchet": {
      "max_enchanting_slots": 18,
      "repair_scaling": 1.0
    },
    "garnished:diamond_hatchet": {
      "max_enchanting_slots": 10,
      "repair_scaling": 0.5
    },
    "garnished:netherite_hatchet": {
      "max_enchanting_slots": 10,
      "repair_scaling": 1.0
    },
    "garnished:jade_hatchet": {
      "max_enchanting_slots": 20,
      "repair_scaling": 3.0
    },
    "garnished:topaz_hatchet": {
      "max_enchanting_slots": 20,
      "repair_scaling": 3.0
    },
    "garnished:sapphire_hatchet": {
      "max_enchanting_slots": 20,
      "repair_scaling": 3.0
    },
    "garnished:ruby_hatchet": {
      "max_enchanting_slots": 20,
      "repair_scaling": 3.0
    },
    "garnished:ametrine_hatchet": {
      "max_enchanting_slots": 20,
      "repair_scaling": 3.0
    },
    "garnished:aquamarine_hatchet": {
      "max_enchanting_slots": 20,
      "repair_scaling": 3.0
    },
    "illagerinvasion:platinum_infused_hatchet": {
      "max_enchanting_slots": 12,
      "repair_scaling": 2.0
    },
    "guarding:netherite_shield": {
      "max_enchanting_slots": 5,
      "repair_scaling": 1.0
    },
    "crossbow_expansion:hand_crossbow": {
      "max_enchanting_slots": 7,
      "repair_scaling": 4.0
    },
    "crossbow_expansion:rage_crossbow": {
      "max_enchanting_slots": 7,
      "repair_scaling": 4.0
    },
    "crossbow_expansion:cluster_crossbow": {
      "max_enchanting_slots": 7,
      "repair_scaling": 4.0
    },
    "crossbow_expansion:pouch_crossbow": {
      "max_enchanting_slots": 7,
      "repair_scaling": 4.0
    },
    "crossbow_expansion:warden_crossbow": {
      "max_enchanting_slots": 7,
      "repair_scaling": 4.0
    },
    "simplyswords:brimstone_claymore": {
      "max_enchanting_slots": 10,
      "repair_scaling": 1.0
    },
    "simplyswords:watcher_claymore": {
      "max_enchanting_slots": 10,
      "repair_scaling": 1.0
    },
    "simplyswords:storms_edge": {
      "max_enchanting_slots": 10,
      "repair_scaling": 1.0
    },
    "simplyswords:stormbringer": {
      "max_enchanting_slots": 10,
      "repair_scaling": 1.0
    },
    "simplyswords:sword_on_a_stick": {
      "max_enchanting_slots": 16,
      "repair_scaling": 2.0
    },
    "simplyswords:bramblethorn": {
      "max_enchanting_slots": 16,
      "repair_scaling": 2.0
    },
    "simplyswords:watching_warglaive": {
      "max_enchanting_slots": 10,
      "repair_scaling": 1.0
    },
    "simplyswords:toxic_longsword": {
      "max_enchanting_slots": 10,
      "repair_scaling": 1.0
    },
    "simplyswords:emberblade": {
      "max_enchanting_slots": 10,
      "repair_scaling": 1.0
    },
    "simplyswords:hearthflame": {
      "max_enchanting_slots": 10,
      "repair_scaling": 1.0
    },
    "simplyswords:soulkeeper": {
      "max_enchanting_slots": 10,
      "repair_scaling": 1.0
    },
    "simplyswords:twisted_blade": {
      "max_enchanting_slots": 10,
      "repair_scaling": 1.0
    },
    "simplyswords:soulstealer": {
      "max_enchanting_slots": 10,
      "repair_scaling": 1.0
    },
    "simplyswords:soulrender": {
      "max_enchanting_slots": 10,
      "repair_scaling": 1.0
    },
    "simplyswords:soulpyre": {
      "max_enchanting_slots": 10,
      "repair_scaling": 1.0
    },
    "simplyswords:frostfall": {
      "max_enchanting_slots": 10,
      "repair_scaling": 1.0
    },
    "simplyswords:molten_edge": {
      "max_enchanting_slots": 10,
      "repair_scaling": 1.0
    },
    "simplyswords:livyatan": {
      "max_enchanting_slots": 10,
      "repair_scaling": 1.0
    },
    "simplyswords:icewhisper": {
      "max_enchanting_slots": 10,
      "repair_scaling": 1.0
    },
    "simplyswords:arcanethyst": {
      "max_enchanting_slots": 10,
      "repair_scaling": 1.0
    },
    "simplyswords:thunderbrand": {
      "max_enchanting_slots": 10,
      "repair_scaling": 1.0
    },
    "simplyswords:mjolnir": {
      "max_enchanting_slots": 10,
      "repair_scaling": 1.0
    },
    "simplyswords:slumbering_lichblade": {
      "max_enchanting_slots": 10,
      "repair_scaling": 1.0
    },
    "simplyswords:waking_lichblade": {
      "max_enchanting_slots": 10,
      "repair_scaling": 1.0
    },
    "simplyswords:awakened_lichblade": {
      "max_enchanting_slots": 10,
      "repair_scaling": 1.0
    },
    "simplyswords:shadowsting": {
      "max_enchanting_slots": 10,
      "repair_scaling": 1.0
    },
    "simplyswords:dormant_relic": {
      "max_enchanting_slots": 10,
      "repair_scaling": 1.0
    },
    "simplyswords:righteous_relic": {
      "max_enchanting_slots": 10,
      "repair_scaling": 1.0
    },
    "simplyswords:tainted_relic": {
      "max_enchanting_slots": 10,
      "repair_scaling": 1.0
    },
    "simplyswords:sunfire": {
      "max_enchanting_slots": 10,
      "repair_scaling": 1.0
    },
    "simplyswords:harbinger": {
      "max_enchanting_slots": 10,
      "repair_scaling": 1.0
    },
    "simplyswords:whisperwind": {
      "max_enchanting_slots": 10,
      "repair_scaling": 1.0
    },
    "simplyswords:emberlash": {
      "max_enchanting_slots": 10,
      "repair_scaling": 1.0
    },
    "simplyswords:waxweaver": {
      "max_enchanting_slots": 10,
      "repair_scaling": 1.0
    },
    "simplyswords:hiveheart": {
      "max_enchanting_slots": 10,
      "repair_scaling": 1.0
    },
    "simplyswords:stars_edge": {
      "max_enchanting_slots": 10,
      "repair_scaling": 1.0
    },
    "simplyswords:wickpiercer": {
      "max_enchanting_slots": 10,
      "repair_scaling": 1.0
    },
    "simplyswords:tempest": {
      "max_enchanting_slots": 10,
      "repair_scaling": 1.0
    }
  }